utility_python_script
