Metadata-Version: 1.0
Name: utility-python-script
Version: 0.0.3
Summary: Utility python scripts
Home-page: https://github.com/eayin2/utility_python_script
Author: eayin2
Author-email: eayin2@gmail.com
License: UNKNOWN
Platform: UNKNOWN
